Strategy/__init__.py
Strategy/bollinger_strategy.py
Strategy/combined_strategy.py
Strategy/kdj_strategy.py
Strategy/turnover_strategy.py
stock_analysis/__init__.py
stock_analysis/stock_analysis.py
tests/__init__.py
tests/test_stock_analysis.py
CHENYE_STOCK_ANALYSIS-0.1.4.dist-info/LICENSE
CHENYE_STOCK_ANALYSIS-0.1.4.dist-info/METADATA
CHENYE_STOCK_ANALYSIS-0.1.4.dist-info/WHEEL
CHENYE_STOCK_ANALYSIS-0.1.4.dist-info/top_level.txt
CHENYE_STOCK_ANALYSIS-0.1.4.dist-info/RECORD
