Metadata-Version: 2.1
Name: CHENYE-STOCK-ANALYSIS
Version: 0.1.4
Summary: A Python library for stock data analysis using BaoStock API
Home-page: https://github.com/CYFearless/CHENYE-STOCK-ANALYSIS
Author: CHEN YE
Author-email: 1765569066@qq.com
Classifier: Programming Language :: Python :: 3
Classifier: License :: OSI Approved :: MIT License
Classifier: Operating System :: OS Independent
Requires-Python: >=3.7
License-File: LICENSE
Requires-Dist: baostock>=0.8.8
Requires-Dist: pandas>=1.3.0
